{
	"name": "ds_synapse_db",
	"properties": {
		"parameters": {
			"schema": {
				"type": "string"
			},
			"table": {
				"type": "string"
			}
		},
		"annotations": [],
		"type": "SqlPoolTable",
		"schema": [],
		"typeProperties": {
			"schema": {
				"value": "@dataset().schema",
				"type": "Expression"
			},
			"table": {
				"value": "@dataset().table",
				"type": "Expression"
			}
		},
		"sqlPool": {
			"referenceName": "test_project",
			"type": "SqlPoolReference"
		}
	},
	"type": "Microsoft.Synapse/workspaces/datasets"
}